github3_utils/__init__.py
github3_utils/apps.py
github3_utils/check_labels.py
github3_utils/click.py
github3_utils/headers.py
github3_utils/py.typed
github3_utils/secrets.py
github3_utils/testing.py
github3_utils-0.7.1.dist-info/LICENSE
github3_utils-0.7.1.dist-info/METADATA
github3_utils-0.7.1.dist-info/WHEEL
github3_utils-0.7.1.dist-info/entry_points.txt
github3_utils-0.7.1.dist-info/RECORD
