Metadata-Version: 2.1
Name: github3-utils
Version: 0.7.1
Summary: Handy utilities for github3.py
Author-email: Dominic Davis-Foster <dominic@davis-foster.co.uk>
License: MIT
Keywords: github
Home-page: https://github.com/domdfcoding/github3-utils
Project-URL: Issue Tracker, https://github.com/domdfcoding/github3-utils/issues
Project-URL: Source Code, https://github.com/domdfcoding/github3-utils
Project-URL: Documentation, https://github3-utils.readthedocs.io/en/latest
Platform: Windows
Platform: macOS
Platform: Linux
Classifier: Development Status :: 4 - Beta
Classifier: Intended Audience :: Developers
Classifier: License :: OSI Approved :: MIT License
Classifier: Operating System :: OS Independent
Classifier: Programming Language :: Python
Classifier: Programming Language :: Python :: 3 :: Only
Classifier: Programming Language :: Python :: 3.6
Classifier: Programming Language :: Python :: 3.7
Classifier: Programming Language :: Python :: 3.8
Classifier: Programming Language :: Python :: 3.9
Classifier: Programming Language :: Python :: 3.10
Classifier: Programming Language :: Python :: 3.11
Classifier: Programming Language :: Python :: Implementation :: CPython
Classifier: Programming Language :: Python :: Implementation :: PyPy
Classifier: Topic :: Software Development :: Libraries :: Python Modules
Classifier: Typing :: Typed
Requires-Python: >=3.6
Requires-Dist: apeye-core>=1.0.0
Requires-Dist: attrs>=20.3.0
Requires-Dist: click>=7.1.2
Requires-Dist: cryptography<40; implementation_name == "pypy" and python_version <= "3.7"
Requires-Dist: domdf-python-tools>=1.1.0
Requires-Dist: github3-py>=1.3.0
Requires-Dist: pynacl>=1.4.0
Requires-Dist: requests>=2.25.1
Requires-Dist: typing-extensions!=3.10.0.1,>=3.10.0.0
Requires-Dist: betamax>=0.8.1; extra == 'testing'
Requires-Dist: pytest>=6.0.0; extra == 'testing'
Requires-Dist: betamax>=0.8.1; extra == 'all'
Requires-Dist: pytest>=6.0.0; extra == 'all'
Provides-Extra: testing
Provides-Extra: all
